[
    {
        "question number": 1.0,
        "question_name": "Question 1.0",
        "type": "matching_question",
        "question_type": "matching_question",
        "points": 1,
        "question text": "What is the chemical formula for Chlorine gas?",
        "url": "",
        "answers": [
            {
                "text": "",
                "answer_text": "Cl₂"
            }
        ],
        "distractors": [
            "Cl",
            "CL",
            "2CL",
            "CL₂",
            "cL",
            "cL₂"
        ]
    },
    {
        "question number": 2.0,
        "question_name": "Question 2.0",
        "type": "matching_question",
        "question_type": "matching_question",
        "points": 1,
        "question text": "How many atoms are in the formula for Chlorine gas?",
        "url": "",
        "answers": [
            {
                "text": "",
                "answer_text": "2"
            }
        ],
        "distractors": [
            "0",
            "1",
            "3",
            "4",
            "5"
        ]
    },
    {
        "question number": 3.0,
        "question_name": "Question 3.0",
        "type": "matching_question",
        "question_type": "matching_question",
        "points": 1,
        "question text": "Which of these is the correct displayed formula for Chlorine gas?",
        "url": "Dot and Cross Diagram 1",
        "answers": [
            {
                "text": "",
                "answer_text": "A"
            }
        ],
        "distractors": [
            "B",
            "C",
            "D"
        ]
    },
    {
        "question number": 4.0,
        "question_name": "Question 4.0",
        "type": "matching_question",
        "question_type": "matching_question",
        "points": 1,
        "question text": "Which of these is the correct Dot and Cross diagram for Chlorine gas?",
        "url": "Dot and Cross Diagram 4",
        "answers": [
            {
                "text": "",
                "answer_text": "B"
            }
        ],
        "distractors": [
            "A",
            "C",
            "D"
        ]
    },
    {
        "question number": 5.0,
        "question_name": "Question 5.0",
        "type": "matching_question",
        "question_type": "matching_question",
        "points": 1,
        "question text": "What is the chemical formula for ammonia?",
        "url": "",
        "answers": [
            {
                "text": "",
                "answer_text": "NH₃"
            }
        ],
        "distractors": [
            "HNHH",
            "NH₂",
            "NH",
            "NH₅",
            "N₂H₂"
        ]
    },
    {
        "question number": 6.0,
        "question_name": "Question 6.0",
        "type": "matching_question",
        "question_type": "matching_question",
        "points": 1,
        "question text": "How many atoms are in the formula for ammonia?",
        "url": "",
        "answers": [
            {
                "text": "",
                "answer_text": "4"
            }
        ],
        "distractors": [
            "0",
            "1",
            "2",
            "3",
            "5"
        ]
    },
    {
        "question number": 7.0,
        "question_name": "Question 7.0",
        "type": "matching_question",
        "question_type": "matching_question",
        "points": 1,
        "question text": "Which of these is the correct displayed formula for ammonia?",
        "url": "Dot and Cross Diagram 5",
        "answers": [
            {
                "text": "",
                "answer_text": "C"
            }
        ],
        "distractors": [
            "A",
            "B",
            "D"
        ]
    },
    {
        "question number": 8.0,
        "question_name": "Question 8.0",
        "type": "matching_question",
        "question_type": "matching_question",
        "points": 1,
        "question text": "Which of these is the correct Dot and Cross diagram for ammonia?",
        "url": "Dot and Cross Diagram 6",
        "answers": [
            {
                "text": "",
                "answer_text": "A"
            }
        ],
        "distractors": [
            "B",
            "C",
            "D"
        ]
    },
    {
        "question number": 9.0,
        "question_name": "Question 9.0",
        "type": "matching_question",
        "question_type": "matching_question",
        "points": 1,
        "question text": "Which of these is the correct Dot and Cross diagram for Hydrogen gas?",
        "url": "Dot and Cross Diagram 3",
        "answers": [
            {
                "text": "",
                "answer_text": "C"
            }
        ],
        "distractors": [
            "A",
            "B",
            "D"
        ]
    },
    {
        "question number": 10.0,
        "question_name": "Question 10.0",
        "type": "matching_question",
        "question_type": "matching_question",
        "points": 1,
        "question text": "What is the chemical formula for Hydrogen gas?",
        "url": "",
        "answers": [
            {
                "text": "",
                "answer_text": "H₂"
            }
        ],
        "distractors": [
            "H",
            "h",
            "h₂",
            "2h",
            "2H"
        ]
    },
    {
        "question number": 11.0,
        "question_name": "Question 11.0",
        "type": "matching_question",
        "question_type": "matching_question",
        "points": 1,
        "question text": "How many atoms are in the formula for Hydrogen gas?",
        "url": "",
        "answers": [
            {
                "text": "",
                "answer_text": "2"
            }
        ],
        "distractors": [
            "0",
            "1",
            "3",
            "4",
            "5"
        ]
    },
    {
        "question number": 12.0,
        "question_name": "Question 12.0",
        "type": "matching_question",
        "question_type": "matching_question",
        "points": 1,
        "question text": "Which of these is the correct displayed formula for Hydrogen gas?",
        "url": "Dot and Cross Diagram 2",
        "answers": [
            {
                "text": "",
                "answer_text": "A"
            }
        ],
        "distractors": [
            "B",
            "C",
            "D"
        ]
    },
    {
        "question number": "Q3",
        "type": "essay_question",
        "points": 0,
        "correct ans index": " ",
        "question text": "Please write your English name used in class:",
        "url": ""
    },
    {
        "question number": "Q4",
        "type": "matching_question",
        "points": 0,
        "correct ans index": " ",
        "question text": "Please select your class:<br>G6A = Grade 6 Class A<br>G6B = Grade 6 Class B<br>G6C = Grade 6 Class C<br>G7A = Grade 7 Class A<br>G7B = Grade 7 Class B<br>G7C = Grade 7 Class C<br>G8A = Grade 8 Class A<br>G8B = Grade 8 Class B<br>G8C = Grade 8 Class C",
        "url": "",
        "a": "G6A",
        "b": "G6B",
        "c": "G6C",
        "d": "G7A",
        "e": "G7B",
        "f": "G7C",
        "g": "G8A",
        "h": "G8B",
        "i": "G8C"
    }
]